teachworks_sdk/__init__.py
teachworks_sdk/errors.py
teachworks_sdk/logging_utils.py
teachworks_sdk/py.typed
teachworks_sdk/session.py
teachworks_sdk/clients/__init__.py
teachworks_sdk/clients/availabilities/__init__.py
teachworks_sdk/clients/availabilities/availabilities.py
teachworks_sdk/clients/availabilities/unavailabilities.py
teachworks_sdk/clients/billing/__init__.py
teachworks_sdk/clients/billing/cost_premiums.py
teachworks_sdk/clients/billing/credit_note_allocations.py
teachworks_sdk/clients/billing/invoices.py
teachworks_sdk/clients/billing/payment_allocations.py
teachworks_sdk/clients/billing/payments.py
teachworks_sdk/clients/employees/__init__.py
teachworks_sdk/clients/employees/employees.py
teachworks_sdk/clients/families/__init__.py
teachworks_sdk/clients/families/customers.py
teachworks_sdk/clients/families/student_groups.py
teachworks_sdk/clients/families/students.py
teachworks_sdk/clients/lessons/__init__.py
teachworks_sdk/clients/lessons/lesson_participants.py
teachworks_sdk/clients/lessons/lessons.py
teachworks_sdk/clients/lessons/other_events.py
teachworks_sdk/clients/outcomes/__init__.py
teachworks_sdk/clients/outcomes/repertoires.py
teachworks_sdk/clients/outcomes/result_groups.py
teachworks_sdk/clients/outcomes/results.py
teachworks_sdk/clients/service_details/__init__.py
teachworks_sdk/clients/service_details/locations.py
teachworks_sdk/clients/service_details/services.py
teachworks_sdk/clients/service_details/subjects.py
teachworks_sdk/clients/wages/__init__.py
teachworks_sdk/clients/wages/other_compensation.py
teachworks_sdk/clients/wages/wage_payments.py
teachworks_sdk/clients/wages/wage_tiers.py
teachworks_sdk/models/__init__.py
teachworks_sdk/models/base.py
teachworks_sdk/models/list_params.py
teachworks_sdk/models/resolvers.py
teachworks_sdk/models/resources.py
teachworks_sdk-1.0.0.dist-info/METADATA
teachworks_sdk-1.0.0.dist-info/WHEEL
teachworks_sdk-1.0.0.dist-info/licenses/LICENSE
teachworks_sdk-1.0.0.dist-info/RECORD
