Metadata-Version: 2.4
Name: teachworks-sdk
Version: 1.0.0
Summary: Python SDK for the Teachworks API.
Project-URL: Homepage, https://github.com/north-star-tutors/Teachworks-SDK
Project-URL: Repository, https://github.com/north-star-tutors/Teachworks-SDK
Project-URL: Documentation, https://github.com/north-star-tutors/Teachworks-SDK#readme
Author: Teachworks SDK Contributors
License: MIT License
License-File: LICENSE
Keywords: api,sdk,teachworks
Classifier: Development Status :: 4 - Beta
Classifier: Intended Audience :: Developers
Classifier: License :: OSI Approved :: MIT License
Classifier: Programming Language :: Python :: 3
Classifier: Programming Language :: Python :: 3.9
Classifier: Programming Language :: Python :: 3.10
Classifier: Programming Language :: Python :: 3.11
Classifier: Programming Language :: Python :: 3.12
Classifier: Typing :: Typed
Requires-Python: >=3.9
Requires-Dist: pydantic>=2.6.0
Requires-Dist: requests>=2.31.0
